<configuration>
    <!-- Console appender with LogstashEncoder -->
    <appender name="CONSOLE" class="ch.qos.logback.core.ConsoleAppender">
        <encoder class="net.logstash.logback.encoder.LogstashEncoder">
            <customFields>{"appname":"webhook-service"}</customFields>
            <includeMdc>true</includeMdc>
            <includeCallerData>true</includeCallerData>
        </encoder>
    </appender>

    <!-- File appender with rolling policy -->
    <appender name="FILE" class="ch.qos.logback.core.rolling.RollingFileAppender">
        <file>logs/application.log</file>
        <rollingPolicy class="ch.qos.logback.core.rolling.TimeBasedRollingPolicy">
            <fileNamePattern>logs/application.%d{yyyy-MM-dd}.log</fileNamePattern>
            <maxHistory>30</maxHistory>
        </rollingPolicy>
        <encoder class="net.logstash.logback.encoder.LogstashEncoder">
            <customFields>{"appname":"webhook-service"}</customFields>
            <includeMdc>true</includeMdc>
            <includeCallerData>true</includeCallerData>
        </encoder>
    </appender>

    <!-- Async appenders -->
    <appender name="ASYNC_CONSOLE" class="ch.qos.logback.classic.AsyncAppender">
        <appender-ref ref="CONSOLE" />
    </appender>
    <appender name="ASYNC_FILE" class="ch.qos.logback.classic.AsyncAppender">
        <appender-ref ref="FILE" />
    </appender>

    <!-- Centralized log management appender (example for Logstash TCP) -->
    <appender name="LOGSTASH" class="net.logstash.logback.appender.LogstashTcpSocketAppender">
        <destination>logstash-host:5000</destination>
        <encoder class="net.logstash.logback.encoder.LogstashEncoder">
            <customFields>{"appname":"webhook-service"}</customFields>
            <includeMdc>true</includeMdc>
            <includeCallerData>true</includeCallerData>
        </encoder>
        <includeCallerData>true</includeCallerData>
    </appender>

    <!-- Root logger with dynamic level control -->
    <root level="INFO">
        <appender-ref ref="ASYNC_CONSOLE" />
        <appender-ref ref="ASYNC_FILE" />
        <appender-ref ref="LOGSTASH" />
    </root>

    <!-- Library loggers -->
    <logger name="org.springframework" level="ERROR" />
    <logger name="org.hibernate" level="ERROR" />

    <!-- Enable JMX for dynamic log level control -->
    <jmxConfigurator />
</configuration>
